cartesi_wallet/__init__.py
cartesi_wallet/balance.py
cartesi_wallet/eth_abi_ext.py
cartesi_wallet/log.py
cartesi_wallet/outputs.py
cartesi_wallet/util.py
cartesi_wallet/wallet.py
cartesi_wallet-0.0.4.dist-info/METADATA
cartesi_wallet-0.0.4.dist-info/WHEEL
cartesi_wallet-0.0.4.dist-info/top_level.txt
cartesi_wallet-0.0.4.dist-info/RECORD
