Metadata-Version: 2.1
Name: cartesi_wallet
Version: 0.0.4
Requires-Dist: cytoolz>=0.12.2
Requires-Dist: requests>=2.31.0
Requires-Dist: eth_abi>=4.0.0
Requires-Dist: routes>=2.5.0
